AUTHORS
ChangeLog
LICENSE
README.md
requirements.txt
setup.cfg
setup.py
test-requirements.txt
tox.ini
skyfree/__init__.py
skyfree.egg-info/PKG-INFO
skyfree.egg-info/SOURCES.txt
skyfree.egg-info/dependency_links.txt
skyfree.egg-info/not-zip-safe
skyfree.egg-info/requires.txt
skyfree.egg-info/top_level.txt
skyfree/collection/__init__.py
skyfree/collection/list/__init__.py
skyfree/collection/list/batch.py
skyfree/datetime/__init__.py
skyfree/datetime/utils.py
skyfree/exception/__init__.py
skyfree/exception/exception.py
skyfree/logger/__init__.py
skyfree/logger/log.py
skyfree/net/__init__.py
skyfree/net/mail/__init__.py
skyfree/net/mail/emailsender.py
skyfree/net/request/__init__.py
skyfree/net/request/client.py
skyfree/reflect/__init__.py
skyfree/reflect/utils.py
skyfree/rtx/__init__.py
skyfree/rtx/sender.py
skyfree/security/__init__.py
skyfree/security/sqlattack/__init__.py
skyfree/security/sqlattack/sql_injection.py
skyfree/serialize/__init__.py
skyfree/serialize/json/__init__.py
skyfree/serialize/json/ajax.py
skyfree/serialize/json/parser.py
skyfree/serialize/json/utils.py
skyfree/serialize/xml/__init__.py
skyfree/struct/__init__.py
skyfree/struct/observer.py
skyfree/struct/singleton.py
skyfree/text/__init__.py
skyfree/text/utils.py
skyfree/thread/__init__.py
skyfree/thread/local.py
skyfree/validator/__init__.py
skyfree/validator/basic.py
skyfree/web/__init__.py
skyfree/web/app/__init__.py
skyfree/web/app/application.py
test/__init__.py
test/test_datetime.py