Metadata-Version: 1.1
Name: skyfree
Version: 0.0.1
Summary: skyfree common lib
Home-page: https://github.com/baotingfang/skyfree-lib
Author: tingfang.bao
Author-email: tingfang.bao@qunar.com
License: Apache -2
Platform: UNKNOWN
Classifier: Intended Audience :: Information Technology
Classifier: Intended Audience :: System Administrators
Classifier: License :: OSI Approved :: Apache Software License
Classifier: Operating System :: POSIX :: Linux
Classifier: Programming Language :: Python
Classifier: Programming Language :: Python :: 2
Classifier: Programming Language :: Python :: 2.7
